research_assistant/__init__.py
research_assistant/__main__.py
research_assistant/app.py
research_assistant/utils.py
research_assistant/agt/__init__.py
research_assistant/agt/dataschema.py
research_assistant/agt/eel.py
research_assistant/agt/patterns.py
research_assistant/agt/versions/CymEng_Cym_GB.json
research_assistant/agt/versions/CymEng_Eng_GB.json
research_assistant/agt/versions/EngZzz_Eng_GB.json
research_assistant/agt/versions/LmoIta_Ita_IT.json
research_assistant/agt/versions/LtzGer_Ger_BE.json
research_assistant/agt/versions/_GerZzz_Ger_DE.json
research_assistant/agt/versions/_ItaZzz_Ita_IT.json
research_assistant/agt/versions/__init__.py
research_assistant/atolc/__init__.py
research_assistant/atolc/patterns.py
research_assistant/atolc/testPyt.py
research_assistant/atolc/versions/CymEng_Cym_GB.json
research_assistant/atolc/versions/CymEng_Eng_GB.json
research_assistant/atolc/versions/EngZzz_Eng_GB.json
research_assistant/atolc/versions/LmoIta_Ita_IT.json
research_assistant/atolc/versions/LtzGer_Ger_BE.json
research_assistant/atolc/versions/_GerZzz_Ger_DE.json
research_assistant/atolc/versions/_ItaZzz_Ita_IT.json
research_assistant/atolc/versions/__init__.py
research_assistant/booteel/__init__.py
research_assistant/conclusion/__init__.py
research_assistant/conclusion/eel.py
research_assistant/conclusion/versions/CymEng_Cym_GB.json
research_assistant/conclusion/versions/CymEng_Eng_GB.json
research_assistant/conclusion/versions/EllEng_Ell_GR.json
research_assistant/conclusion/versions/EngZzz_Eng_GB.json
research_assistant/conclusion/versions/GswGer_Ger_DE.json
research_assistant/conclusion/versions/LmoIta_Ita_IT.json
research_assistant/conclusion/versions/LtzGer_Ger_BE.json
research_assistant/conclusion/versions/__init__.py
research_assistant/config/__init__.py
research_assistant/consent/__init__.py
research_assistant/consent/versions/CymEng_Eng_GB.agt.json
research_assistant/consent/versions/CymEng_Eng_GB.atol.json
lart_research_assistant-0.5.0.dist-info/LICENSE
lart_research_assistant-0.5.0.dist-info/LICENSE.AGPL-3.0
lart_research_assistant-0.5.0.dist-info/LICENSE.EUPL-1.2
lart_research_assistant-0.5.0.dist-info/METADATA
lart_research_assistant-0.5.0.dist-info/WHEEL
lart_research_assistant-0.5.0.dist-info/entry_points.txt
lart_research_assistant-0.5.0.dist-info/top_level.txt
lart_research_assistant-0.5.0.dist-info/RECORD
