Metadata-Version: 2.1
Name: lart-research-assistant
Version: 0.5.0
Summary: An app that aims to make life easier for researchers working on bilingualism, sociolinguistics, language attitudes, and regional/minority/minoritized languages.
Home-page: https://github.com/lart-bangor/research-assistant
Author: Florian Breit, Marco Tamburelli
Author-email: f.breit@bangor.ac.uk
License: AGPLv3-or-later OR EUPL-1.2+
Project-URL: Documentation, https://research-assistant.readthedocs.io/
Project-URL: Bug Tracker, https://github.com/lart-bangor/research-assistant/issues
Project-URL: Support, https://github.com/lart-bangor/research-assistant/discussions
Project-URL: Source, https://github.com/lart-bangor/research-assistant
Classifier: Development Status :: 4 - Beta
Classifier: Intended Audience :: Education
Classifier: Intended Audience :: Science/Research
Classifier: Intended Audience :: End Users/Desktop
Classifier: License :: OSI Approved :: GNU Affero General Public License v3 or later (AGPLv3+)
Classifier: License :: OSI Approved :: European Union Public Licence 1.2 (EUPL 1.2)
Classifier: Natural Language :: English
Classifier: Natural Language :: German
Classifier: Natural Language :: Italian
Classifier: Natural Language :: Greek
Classifier: Operating System :: Microsoft :: Windows :: Windows 10
Classifier: Operating System :: Microsoft :: Windows :: Windows 11
Classifier: Operating System :: POSIX :: Linux
Classifier: Operating System :: MacOS
Classifier: Programming Language :: Python :: 3.10
Classifier: Programming Language :: JavaScript
Classifier: Topic :: Scientific/Engineering
Classifier: Topic :: Sociology
Classifier: Topic :: Text Processing :: Linguistic
Classifier: Topic :: Utilities
Requires-Python: >=3.10
License-File: LICENSE
License-File: LICENSE.AGPL-3.0
License-File: LICENSE.EUPL-1.2
Requires-Dist: greenlet (<2.0.0)
Requires-Dist: gevent (<22.10.0)
Requires-Dist: eel[jinja2] (==0.16.0)
Requires-Dist: platformdirs (==3.2.0)
